README.rst
setup.py
image_diet/__init__.py
image_diet/diet.py
image_diet/models.py
image_diet/settings.py
image_diet/signals.py
image_diet.egg-info/PKG-INFO
image_diet.egg-info/SOURCES.txt
image_diet.egg-info/dependency_links.txt
image_diet.egg-info/not-zip-safe
image_diet.egg-info/requires.txt
image_diet.egg-info/top_level.txt
image_diet/management/__init__.py
image_diet/management/commands/__init__.py
image_diet/management/commands/check_diet_tools.py
image_diet/management/commands/diet_images.py
image_diet/tests/__init__.py
image_diet/tests/test_commands.py
image_diet/tests/test_diet.py