Metadata-Version: 1.0
Name: image-diet
Version: 0.7
Summary: Remove unnecessary bytes from images
Home-page: https://github.com/samastur/image-diet/
Author: Marko Samastur
Author-email: markos@gaivo.net
License: MIT License
Platform: OS Independent
Classifier: Development Status :: 4 - Beta
Classifier: Environment :: Web Environment
Classifier: Intended Audience :: Developers
Classifier: Operating System :: OS Independent
Classifier: Programming Language :: Python
Classifier: Framework :: Django
Classifier: Topic :: Utilities
